aperture_sdk/__init__.py
aperture_sdk/_gen/__init__.py
aperture_sdk/_gen/aperture/__init__.py
aperture_sdk/_gen/aperture/flowcontrol/__init__.py
aperture_sdk/_gen/aperture/flowcontrol/check/__init__.py
aperture_sdk/_gen/aperture/flowcontrol/check/v1/__init__.py
aperture_sdk/_gen/aperture/flowcontrol/check/v1/check_pb2.py
aperture_sdk/_gen/aperture/flowcontrol/check/v1/check_pb2.pyi
aperture_sdk/_gen/aperture/flowcontrol/check/v1/check_pb2_grpc.py
aperture_sdk/cache.py
aperture_sdk/client.py
aperture_sdk/client_async.py
aperture_sdk/client_common.py
aperture_sdk/const.py
aperture_sdk/flow.py
aperture_sdk/flow_async.py
aperture_sdk/flow_common.py
aperture_sdk/utils.py
aperture_py-2.26.0.dist-info/METADATA
aperture_py-2.26.0.dist-info/WHEEL
aperture_py-2.26.0.dist-info/RECORD
